aiofast/__init__.py
aiofast/exceptions.py
aiofast/handler.py
aiofast-0.0.2.dist-info/METADATA
aiofast-0.0.2.dist-info/WHEEL
aiofast-0.0.2.dist-info/licenses/LICENSE
aiofast-0.0.2.dist-info/RECORD
