Metadata-Version: 2.1
Name: aiofast
Version: 0.0.2
Summary: A simple aiohttp library to quickly write api.
Project-URL: Homepage, https://github.com/daniil-grois/aiofast
Project-URL: Documentation, https://github.com/daniil-grois/aiofast
Author-email: Daniil Grois <daniil.grois@gmail.com>
License-File: LICENSE
Classifier: Environment :: Web Environment
Classifier: Framework :: AsyncIO
Classifier: Intended Audience :: Developers
Classifier: Intended Audience :: Information Technology
Classifier: Intended Audience :: System Administrators
Classifier: License :: OSI Approved :: MIT License
Classifier: Operating System :: OS Independent
Classifier: Programming Language :: Python
Classifier: Programming Language :: Python :: 3
Classifier: Programming Language :: Python :: 3 :: Only
Classifier: Programming Language :: Python :: 3.9
Classifier: Topic :: Internet
Classifier: Topic :: Internet :: WWW/HTTP
Classifier: Topic :: Software Development
Classifier: Topic :: Software Development :: Libraries
Classifier: Topic :: Software Development :: Libraries :: Python Modules
Classifier: Typing :: Typed
Requires-Python: >=3.9
Requires-Dist: aiohttp==3.8.3
Requires-Dist: dependency-injector<5.0.0,>=4.40.0
Requires-Dist: pydantic<2.0.0,>=1.10.2
Provides-Extra: dev
Requires-Dist: pre-commit<3.0.0,>=2.17.0; extra == 'dev'
Provides-Extra: test
Requires-Dist: isort<6.0.0,>=5.10.1; extra == 'test'
Requires-Dist: mypy==0.982; extra == 'test'
Requires-Dist: pytest<8.0.0,>=7.1.3; extra == 'test'
Requires-Dist: wemake-python-styleguide==0.17.0; extra == 'test'
